timetric
