Metadata-Version: 1.0
Name: timetric
Version: 1.3
Summary: Client library for Timetric (http://timetric.com/)
Home-page: http://github.com/jacobian/timetric
Author: Jacob Kaplan-Moss
Author-email: jacob@jaobian.org
License: UNKNOWN
Platform: UNKNOWN
Classifier: Development Status :: 4 - Beta
Classifier: Intended Audience :: Developers
Classifier: License :: OSI Approved :: BSD License
Classifier: Operating System :: OS Independent
Classifier: Programming Language :: Python
Classifier: Topic :: Internet
